[
  {
    "code": "2337",
    "name": "旺宏",
    "industry": "半導體",
    "concepts": ["記憶體", "NOR Flash"],
    "close": 155.5,
    "changePercent": -1.89,
    "volume": 99766973,
    "turnoverRate": 5.04,
    "fundamentalScore": 82,
    "technicalScore": 72,
    "chipScore": 76,
    "turnoverScore": 84,
    "totalScore": 0,
    "tradeType": "波段",
    "riskLabel": "正常",
    "updatedAt": "2026-07-01"
  },
  {
    "code": "2313",
    "name": "華通",
    "industry": "電子零組件",
    "concepts": ["PCB", "低基期補漲"],
    "close": 232.5,
    "changePercent": 5.2,
    "volume": 26497727,
    "turnoverRate": 2.22,
    "fundamentalScore": 70,
    "technicalScore": 78,
    "chipScore": 73,
    "turnoverScore": 68,
    "totalScore": 0,
    "tradeType": "波段",
    "riskLabel": "正常",
    "updatedAt": "2026-07-01"
  },
  {
    "code": "3037",
    "name": "欣興",
    "industry": "電子零組件",
    "concepts": ["PCB", "ABF 載板"],
    "close": 1070,
    "changePercent": 9.63,
    "volume": 33861853,
    "turnoverRate": 2.13,
    "fundamentalScore": 78,
    "technicalScore": 88,
    "chipScore": 82,
    "turnoverScore": 76,
    "totalScore": 0,
    "tradeType": "短線",
    "riskLabel": "過熱",
    "updatedAt": "2026-07-01"
  },
  {
    "code": "6442",
    "name": "光聖",
    "industry": "通信網路",
    "concepts": ["CPO", "光通訊"],
    "close": 1640,
    "changePercent": 2.5,
    "volume": 1815275,
    "turnoverRate": 2.33,
    "fundamentalScore": 88,
    "technicalScore": 85,
    "chipScore": 80,
    "turnoverScore": 74,
    "totalScore": 0,
    "tradeType": "波段",
    "riskLabel": "過熱",
    "updatedAt": "2026-07-01"
  },
  {
    "code": "2327",
    "name": "國巨",
    "industry": "電子零組件",
    "concepts": ["被動元件", "MLCC"],
    "close": 1140,
    "changePercent": 9.62,
    "volume": 57942123,
    "turnoverRate": 2.8,
    "fundamentalScore": 84,
    "technicalScore": 90,
    "chipScore": 86,
    "turnoverScore": 82,
    "totalScore": 0,
    "tradeType": "短線",
    "riskLabel": "過熱",
    "updatedAt": "2026-07-01"
  }
]
